MANIFEST.in
README.md
requirements.txt
setup.py
dmarchiver/__init__.py
dmarchiver/cmdline.py
dmarchiver/core.py
dmarchiver.egg-info/PKG-INFO
dmarchiver.egg-info/SOURCES.txt
dmarchiver.egg-info/dependency_links.txt
dmarchiver.egg-info/entry_points.txt
dmarchiver.egg-info/requires.txt
dmarchiver.egg-info/top_level.txt