Metadata-Version: 1.1
Name: dmarchiver
Version: 0.2.5
Summary: A tool to archive the direct messages from your private conversations on Twitter.
Home-page: https://github.com/Mincka/DMArchiver
Author: Julien EHRHART
Author-email: julien.ehrhart@live.com
License: GNU General Public License v3 (GPLv3)
Platform: UNKNOWN
Classifier: Programming Language :: Python
Classifier: Development Status :: 3 - Alpha
Classifier: License :: OSI Approved
Classifier: Natural Language :: English
Classifier: Operating System :: OS Independent
Classifier: Programming Language :: Python :: 3.5
Classifier: Topic :: System :: Archiving
Classifier: License :: OSI Approved :: GNU General Public License v3 (GPLv3)
